{"text":"Floor length chiffon bridesmaid dress with pleated bodice and V neckline available in sage and dusty blue","labels":{"Silhouette":"A-line","Fabric":"chiffon","Neckline":"V neckline","Sleeve":"sleeveless","Length":"floor length","Embellishment":"pleated bodice","Color":"sage; dusty blue","Category":"bridesmaid dress"}}
{"text":"Sparkly sequin fitted prom gown featuring a deep illusion neckline and open back","labels":{"Silhouette":"fitted","Fabric":"sequin","Neckline":"illusion neckline","Sleeve":"sleeveless","Length":"floor length","Embellishment":"sparkly; open back","Color":"silver","Category":"prom gown"}}
{"text":"Off shoulder satin ball gown with corset bodice and sweep train in royal navy","labels":{"Silhouette":"ball gown","Fabric":"satin","Neckline":"off shoulder","Sleeve":"off shoulder","Length":"floor length; sweep train","Embellishment":"corset bodice","Color":"royal navy","Category":"ball gown"}}
{"text":"Lace mermaid wedding dress with long sleeves and scalloped hem","labels":{"Silhouette":"mermaid","Fabric":"lace","Neckline":"sweetheart","Sleeve":"long sleeves","Length":"floor length","Embellishment":"scalloped hem","Color":"ivory","Category":"wedding dress"}}
{"text":"Short cocktail dress with feather trim and beaded waist detail","labels":{"Silhouette":"sheath","Fabric":"unknown","Neckline":"round neckline","Sleeve":"sleeveless","Length":"short","Embellishment":"feather trim; beaded waist","Color":"black","Category":"cocktail dress"}}
{"text":"Tulle A line evening gown with floral embroidery and cap sleeves","labels":{"Silhouette":"A-line","Fabric":"tulle","Neckline":"V neckline","Sleeve":"cap sleeves","Length":"floor length","Embellishment":"floral embroidery","Color":"blush","Category":"evening gown"}}
{"text":"Stretch jersey sheath dress with ruched waist and side slit","labels":{"Silhouette":"sheath","Fabric":"stretch jersey","Neckline":"boat neckline","Sleeve":"sleeveless","Length":"knee length","Embellishment":"ruched waist; side slit","Color":"navy","Category":"sheath dress"}}
{"text":"Strapless sweetheart neckline glitter gown with layered skirt","labels":{"Silhouette":"fit-and-flare","Fabric":"glitter","Neckline":"sweetheart","Sleeve":"strapless","Length":"floor length","Embellishment":"layered skirt","Color":"gold","Category":"gown"}}
{"text":"One shoulder draped chiffon dress with high slit and empire waist","labels":{"Silhouette":"column","Fabric":"chiffon","Neckline":"one shoulder","Sleeve":"one shoulder","Length":"floor length","Embellishment":"draped; high slit","Color":"emerald","Category":"evening dress"}}
{"text":"Velvet winter formal dress with square neckline and puff sleeves","labels":{"Silhouette":"A-line","Fabric":"velvet","Neckline":"square neckline","Sleeve":"puff sleeves","Length":"midi","Embellishment":"none","Color":"burgundy","Category":"formal dress"}}
{"text":"High low chiffon cocktail dress with beaded straps and ruched bodice in champagne","labels":{"Silhouette":"high-low","Fabric":"chiffon","Neckline":"V neckline","Sleeve":"spaghetti straps","Length":"high-low","Embellishment":"beaded straps; ruched bodice","Color":"champagne","Category":"cocktail dress"}}
{"text":"Sequin mermaid gown with plunging V neckline and illusion mesh panels","labels":{"Silhouette":"mermaid","Fabric":"sequin","Neckline":"plunging V","Sleeve":"sleeveless","Length":"floor length","Embellishment":"illusion mesh panels","Color":"rose gold","Category":"gown"}}
{"text":"Tea length organza dress with bateau neckline and three quarter sleeves","labels":{"Silhouette":"A-line","Fabric":"organza","Neckline":"bateau neckline","Sleeve":"three quarter sleeves","Length":"tea length","Embellishment":"none","Color":"ivory","Category":"day dress"}}
{"text":"Pleated satin slip dress with cowl neckline and adjustable straps","labels":{"Silhouette":"slip","Fabric":"satin","Neckline":"cowl neckline","Sleeve":"spaghetti straps","Length":"midi","Embellishment":"pleated","Color":"emerald","Category":"slip dress"}}
{"text":"Velvet sheath dress with mock neck and long fitted sleeves","labels":{"Silhouette":"sheath","Fabric":"velvet","Neckline":"mock neck","Sleeve":"long fitted sleeves","Length":"knee length","Embellishment":"none","Color":"black","Category":"sheath dress"}}
{"text":"Beaded A line wedding gown with illusion long sleeves and cathedral train","labels":{"Silhouette":"A-line","Fabric":"tulle; lace","Neckline":"illusion neckline","Sleeve":"long sleeves","Length":"floor length; cathedral train","Embellishment":"beaded","Color":"ivory","Category":"wedding gown"}}
{"text":"Mini sequin party dress with halter neckline and open back","labels":{"Silhouette":"mini","Fabric":"sequin","Neckline":"halter neckline","Sleeve":"sleeveless","Length":"mini","Embellishment":"open back","Color":"black","Category":"party dress"}}
{"text":"Satin wrap dress with ruffle hem and elbow length sleeves in dusty rose","labels":{"Silhouette":"wrap","Fabric":"satin","Neckline":"wrap V","Sleeve":"elbow length","Length":"midi","Embellishment":"ruffle hem","Color":"dusty rose","Category":"wrap dress"}}
{"text":"Embroidered tulle prom dress with illusion back and cap sleeves","labels":{"Silhouette":"A-line","Fabric":"tulle","Neckline":"illusion neckline","Sleeve":"cap sleeves","Length":"floor length","Embellishment":"embroidered; illusion back","Color":"ivory; blush","Category":"prom dress"}}
{"text":"One shoulder velvet cocktail dress with asymmetric hem and ruching","labels":{"Silhouette":"asymmetric","Fabric":"velvet","Neckline":"one shoulder","Sleeve":"one shoulder","Length":"knee length","Embellishment":"ruching","Color":"emerald","Category":"cocktail dress"}}
{"text":"Halter neck chiffon maxi dress with smocked waist and tiered skirt","labels":{"Silhouette":"maxi","Fabric":"chiffon","Neckline":"halter neck","Sleeve":"sleeveless","Length":"floor length","Embellishment":"tiered skirt; smocked waist","Color":"navy floral","Category":"maxi dress"}}
{"text":"Cap sleeve lace tea dress with scalloped neckline and fitted waist","labels":{"Silhouette":"fit-and-flare","Fabric":"lace","Neckline":"scalloped neckline","Sleeve":"cap sleeves","Length":"tea length","Embellishment":"scalloped hem","Color":"ivory","Category":"tea dress"}}
{"text":"Asymmetric one shoulder sequin gown with thigh high slit and open back","labels":{"Silhouette":"asymmetric","Fabric":"sequin","Neckline":"one shoulder","Sleeve":"one shoulder","Length":"floor length","Embellishment":"thigh high slit; open back","Color":"black","Category":"gown"}}
{"text":"Tiered tulle mini dress with puff sleeves and bow waist in pale pink","labels":{"Silhouette":"tiered","Fabric":"tulle","Neckline":"round neckline","Sleeve":"puff sleeves","Length":"mini","Embellishment":"bow waist","Color":"pale pink","Category":"party dress"}}
{"text":"Satin halter mermaid dress with lace appliqué and sweep train","labels":{"Silhouette":"mermaid","Fabric":"satin","Neckline":"halter neckline","Sleeve":"sleeveless","Length":"floor length; sweep train","Embellishment":"lace appliqué","Color":"ivory","Category":"wedding dress"}}
{"text":"Off shoulder floral print midi dress with ruffled sleeves","labels":{"Silhouette":"A-line","Fabric":"cotton blend","Neckline":"off shoulder","Sleeve":"ruffled sleeves","Length":"midi","Embellishment":"floral print; ruffles","Color":"multicolor floral","Category":"day dress"}}
{"text":"Sequin fringe mini dress with scoop neckline and long sleeves","labels":{"Silhouette":"mini","Fabric":"sequin","Neckline":"scoop neckline","Sleeve":"long sleeves","Length":"mini","Embellishment":"fringe","Color":"gold","Category":"party dress"}}
{"text":"High neck lace sheath with cap sleeves and keyhole back","labels":{"Silhouette":"sheath","Fabric":"lace","Neckline":"high neck","Sleeve":"cap sleeves","Length":"knee length","Embellishment":"keyhole back","Color":"ivory","Category":"cocktail dress"}}
{"text":"Draped jersey evening gown with cowl back and side ruching","labels":{"Silhouette":"draped","Fabric":"jersey","Neckline":"cowl neckline","Sleeve":"sleeveless","Length":"floor length","Embellishment":"side ruching; cowl back","Color":"midnight blue","Category":"evening gown"}}
{"text":"Ball gown with embroidered bodice, off shoulder sleeves and chapel train","labels":{"Silhouette":"ball gown","Fabric":"tulle; lace","Neckline":"off shoulder","Sleeve":"off shoulder","Length":"floor length; chapel train","Embellishment":"embroidered bodice","Color":"ivory","Category":"bridal gown"}}
{"text":"Sheer illusion long sleeve wedding dress with beaded fringe and mermaid skirt","labels":{"Silhouette":"mermaid","Fabric":"illusion tulle","Neckline":"illusion neckline","Sleeve":"long sleeves","Length":"floor length","Embellishment":"beaded fringe","Color":"ivory","Category":"wedding dress"}}
{"text":"Satin peplum cocktail dress with square neckline and cap sleeves","labels":{"Silhouette":"peplum","Fabric":"satin","Neckline":"square neckline","Sleeve":"cap sleeves","Length":"knee length","Embellishment":"peplum","Color":"red","Category":"cocktail dress"}}
{"text":"Velvet wrap maxi dress with long bishop sleeves and tie waist","labels":{"Silhouette":"wrap","Fabric":"velvet","Neckline":"wrap V","Sleeve":"bishop sleeves","Length":"maxi","Embellishment":"tie waist","Color":"plum","Category":"maxi dress"}}
{"text":"Beaded fringe flapper dress with V neckline and sleeveless cut","labels":{"Silhouette":"shift","Fabric":"beaded","Neckline":"V neckline","Sleeve":"sleeveless","Length":"knee length","Embellishment":"beaded fringe","Color":"champagne","Category":"vintage party dress"}}
{"text":"One shoulder satin mini with draped bodice and ruched side","labels":{"Silhouette":"mini","Fabric":"satin","Neckline":"one shoulder","Sleeve":"one shoulder","Length":"mini","Embellishment":"draped bodice; ruched side","Color":"black","Category":"party dress"}}
{"text":"Embroidered chiffon maxi with V neckline and flutter sleeves","labels":{"Silhouette":"maxi","Fabric":"chiffon","Neckline":"V neckline","Sleeve":"flutter sleeves","Length":"floor length","Embellishment":"embroidered","Color":"ivory floral","Category":"maxi dress"}}
{"text":"Sequin column gown with bateau neckline and cap sleeves","labels":{"Silhouette":"column","Fabric":"sequin","Neckline":"bateau neckline","Sleeve":"cap sleeves","Length":"floor length","Embellishment":"sequin","Color":"silver","Category":"gown"}}
{"text":"Short lace dress with illusion neckline and scalloped hem in blush","labels":{"Silhouette":"fit-and-flare","Fabric":"lace","Neckline":"illusion neckline","Sleeve":"sleeveless","Length":"short","Embellishment":"scalloped hem","Color":"blush","Category":"party dress"}}
{"text":"Velvet corset dress with sweetheart neckline and lace up back","labels":{"Silhouette":"fit-and-flare","Fabric":"velvet","Neckline":"sweetheart","Sleeve":"sleeveless","Length":"midi","Embellishment":"corset; lace up back","Color":"emerald","Category":"evening dress"}}
{"text":"Tulle princess dress with puff sleeves and crystal beading","labels":{"Silhouette":"princess","Fabric":"tulle","Neckline":"round neckline","Sleeve":"puff sleeves","Length":"floor length","Embellishment":"crystal beading","Color":"ivory","Category":"bridal gown"}}
{"text":"Satin column dress with square back and spaghetti straps","labels":{"Silhouette":"column","Fabric":"satin","Neckline":"square back","Sleeve":"spaghetti straps","Length":"floor length","Embellishment":"none","Color":"navy","Category":"evening dress"}}
{"text":"Ruffled chiffon mini with off shoulder neckline and elastic waist","labels":{"Silhouette":"mini","Fabric":"chiffon","Neckline":"off shoulder","Sleeve":"short ruffle sleeves","Length":"mini","Embellishment":"ruffles","Color":"coral","Category":"summer dress"}}
{"text":"Beaded illusion bodice wedding dress with trumpet skirt and chapel train","labels":{"Silhouette":"trumpet","Fabric":"tulle; lace","Neckline":"illusion neckline","Sleeve":"sleeveless","Length":"floor length; chapel train","Embellishment":"beaded illusion bodice","Color":"ivory","Category":"wedding dress"}}
{"text":"Sequin halter mini with open back and scalloped hem","labels":{"Silhouette":"mini","Fabric":"sequin","Neckline":"halter neckline","Sleeve":"sleeveless","Length":"mini","Embellishment":"open back; scalloped hem","Color":"rose","Category":"party dress"}}
{"text":"Lace A line dress with bateau neckline and three quarter illusion sleeves","labels":{"Silhouette":"A-line","Fabric":"lace","Neckline":"bateau neckline","Sleeve":"three quarter illusion sleeves","Length":"midi","Embellishment":"lace","Color":"ivory","Category":"day dress"}}
{"text":"Glitter tulle prom dress with sweetheart neckline and layered skirt","labels":{"Silhouette":"fit-and-flare","Fabric":"glitter tulle","Neckline":"sweetheart","Sleeve":"strapless","Length":"floor length","Embellishment":"layered skirt","Color":"champagne","Category":"prom dress"}}
{"text":"Satin one shoulder gown with asymmetric drape and thigh slit","labels":{"Silhouette":"asymmetric","Fabric":"satin","Neckline":"one shoulder","Sleeve":"one shoulder","Length":"floor length","Embellishment":"asymmetric drape; thigh slit","Color":"ruby","Category":"gown"}}
{"text":"Cotton sundress with square neckline and tie straps in lemon print","labels":{"Silhouette":"sundress","Fabric":"cotton","Neckline":"square neckline","Sleeve":"sleeveless","Length":"knee length","Embellishment":"tie straps; print","Color":"lemon print","Category":"casual dress"}}
{"text":"Velvet mini dress with mock neck and long balloon sleeves","labels":{"Silhouette":"mini","Fabric":"velvet","Neckline":"mock neck","Sleeve":"balloon sleeves","Length":"mini","Embellishment":"none","Color":"midnight","Category":"party dress"}}
{"text":"Embroidered sheath with cap sleeves and jewel neckline","labels":{"Silhouette":"sheath","Fabric":"embroidered fabric","Neckline":"jewel neckline","Sleeve":"cap sleeves","Length":"knee length","Embellishment":"embroidery","Color":"ivory","Category":"cocktail dress"}}
{"text":"Tulle layered ball gown with crystal bodice and cathedral train","labels":{"Silhouette":"ball gown","Fabric":"tulle","Neckline":"sweetheart","Sleeve":"strapless","Length":"floor length; cathedral train","Embellishment":"crystal bodice","Color":"ivory","Category":"bridal gown"}}
